ft_hubspot_workflow_backup/__init__.py
ft_hubspot_workflow_backup/backup.py
ft_hubspot_workflow_backup/client.py
ft_hubspot_workflow_backup/restore.py
ft_hubspot_workflow_backup/validate.py
ft_hubspot_workflow_backup-0.1.6.dist-info/METADATA
ft_hubspot_workflow_backup-0.1.6.dist-info/WHEEL
ft_hubspot_workflow_backup-0.1.6.dist-info/entry_points.txt
ft_hubspot_workflow_backup-0.1.6.dist-info/licenses/LICENSE
ft_hubspot_workflow_backup-0.1.6.dist-info/RECORD
