Metadata-Version: 2.4
Name: ft-hubspot-workflow-backup
Version: 0.1.6
Summary: Backup and restore HubSpot Automation (v4) workflows
Project-URL: Homepage, https://github.com/nflore/ft-hubspot-workflow-backup
Project-URL: Repository, https://github.com/nflore/ft-hubspot-workflow-backup
Project-URL: Issues, https://github.com/nflore/ft-hubspot-workflow-backup/issues
Project-URL: Changelog, https://github.com/nflore/ft-hubspot-workflow-backup/releases
Author: Nathan Flore
License-Expression: MIT
License-File: LICENSE
Requires-Python: >=3.9
Requires-Dist: requests>=2.25.0
